blitz_parse-0.1.0.dist-info/METADATA
blitz_parse-0.1.0.dist-info/WHEEL
blitz_parse.libs/libbz2-3265f064.so.1.0
blitz_parse/__init__.py
blitz_parse/blitz_parse.abi3.so
blitz_parse-0.1.0.dist-info/RECORD
