Metadata-Version: 2.4
Name: blitz_parse
Version: 0.1.0
